l9format/__init__.py
l9format/l9format.py
l9format-1.3.2.dist-info/LICENSE
l9format-1.3.2.dist-info/METADATA
l9format-1.3.2.dist-info/WHEEL
l9format-1.3.2.dist-info/RECORD
