Metadata-Version: 2.3
Name: l9format
Version: 1.3.2
Summary: l9format is a schema declaration targeted at interoperability between network recon tools used at LeakIX
License: MIT
Author: Danny Willems
Author-email: danny@leakix.net
Maintainer: Danny Willems
Maintainer-email: danny@leakix.net
Requires-Python: >=3.9,<4.0
Classifier: License :: OSI Approved :: MIT License
Classifier: Programming Language :: Python :: 3
Classifier: Programming Language :: Python :: 3.9
Classifier: Programming Language :: Python :: 3.10
Classifier: Programming Language :: Python :: 3.11
Classifier: Programming Language :: Python :: 3.12
Classifier: Programming Language :: Python :: 3.13
Requires-Dist: serde (>=0.8.1,<0.9.0)
Project-URL: Bug Tracker, https://github.com/leakix/l9format-python/issues
Project-URL: Documentation, https://github.com/leakix/l9format-python
Project-URL: Homepage, https://github.com/leakix/l9format-python
Project-URL: Repository, https://github.com/leakix/l9format-python
